instrumess/__init__.py
instrumess/Examples/Dynamic plot.py
instrumess/Examples/__init__.py
instrumess/Examples/ex1_LIV_curve.py
instrumess/Examples/templ1_Instrument_driver.py
instrumess/analysis/2019-03-03 Gain saturation.py
"instrumess/analysis/2019-03-20 Saturation, 500um.py"
"instrumess/analysis/2019-03-20 Saturation, flat power.py"
instrumess/analysis/2019-03-29 BPF ins_loss variation.py
instrumess/analysis/__init__.py
instrumess/analysis/gain_mult_wg.py
instrumess/analysis/gain_saturation.py
instrumess/analysis/liv.py
instrumess/analysis/optimization.py
instrumess/analysis/spectrum.py
instrumess/analysis/test.py
instrumess/instruments/Agilent_PM.py
instrumess/instruments/Agilent_TLS.py
instrumess/instruments/Ando.py
instrumess/instruments/Apex_new.py
instrumess/instruments/Apex_old.py
instrumess/instruments/BPF.py
instrumess/instruments/Keithley2400.py
instrumess/instruments/Keithley2450.py
instrumess/instruments/Keithley2602B.py
instrumess/instruments/LDC.py
instrumess/instruments/LeCroy.py
instrumess/instruments/NI_daq.py
instrumess/instruments/SantecTLS.py
instrumess/instruments/TEC.py
instrumess/instruments/VOA.py
instrumess/instruments/WM.py
instrumess/instruments/Yokogawa.py
instrumess/instruments/__init__.py
instrumess/instruments/instrument.py
instrumess/utilities/__init__.py
instrumess/utilities/dotdict.py
instrumess/utilities/dynamic_plot.py
instrumess/utilities/e('@').py
instrumess/utilities/findpeaks.py
instrumess/utilities/load.py
instrumess/utilities/plot_aux.py
instrumess/utilities/utilities.py
instrumess/utilities/validate.py
instrumess-0.2.0.dist-info/License.txt
instrumess-0.2.0.dist-info/METADATA
instrumess-0.2.0.dist-info/WHEEL
instrumess-0.2.0.dist-info/top_level.txt
instrumess-0.2.0.dist-info/RECORD
