Metadata-Version: 2.1
Name: instrumess
Version: 0.2.0
Summary: Instrument drivers for PhDs in Photonics
Home-page: https://gitlab.tue.nl/20171304/instrumess.git
Author: Rastko Pajković
Author-email: r.pajkovic@tue.nl
License: AGNU3
Keywords: photonics measurement instrument automation
Platform: UNKNOWN
Classifier: Development Status :: 3 - Alpha
Classifier: License :: OSI Approved :: GNU General Public License v3 or later (GPLv3+)
Classifier: Programming Language :: Python :: 3.7
Classifier: Topic :: Scientific/Engineering :: Human Machine Interfaces
Requires-Dist: pyvisa
Requires-Dist: pandas
Requires-Dist: pathlib
